lts_workflows/__init__.py
lts_workflows/_version.py
lts_workflows/utils.py
lts_workflows/pytest/__init__.py
lts_workflows/pytest/factories.py
lts_workflows/pytest/helpers.py
lts_workflows/pytest/plugin.py
lts_workflows/snakemake/__init__.py
lts_workflows/snakemake/config.py
lts_workflows-0.2.5.data/scripts/deploy_workflow.py
lts_workflows-0.2.5.dist-info/DESCRIPTION.rst
lts_workflows-0.2.5.dist-info/METADATA
lts_workflows-0.2.5.dist-info/RECORD
lts_workflows-0.2.5.dist-info/WHEEL
lts_workflows-0.2.5.dist-info/entry_points.txt
lts_workflows-0.2.5.dist-info/metadata.json
lts_workflows-0.2.5.dist-info/top_level.txt
