Metadata-Version: 2.0
Name: lts-workflows
Version: 0.2.5
Summary: SciLifeLab long-term support workflows
Home-page: https://bitbucket.org/scilifelab-lts/lts-workflows
Author: Per Unneberg
Author-email: per.unneberg@scilifelab.se
License: GNU General Public License v3
Keywords: lts_workflows
Platform: UNKNOWN
Classifier: Development Status :: 2 - Pre-Alpha
Classifier: Intended Audience :: Developers
Classifier: License :: OSI Approved :: GNU General Public License v3 (GPLv3)
Classifier: Natural Language :: English
Classifier: Programming Language :: Python :: 3
Classifier: Programming Language :: Python :: 3.3
Classifier: Programming Language :: Python :: 3.4
Classifier: Programming Language :: Python :: 3.5
Requires-Dist: pytest (>=3.0.4)
Requires-Dist: pyyaml
Requires-Dist: snakemake (>=3.10.0)
Requires-Dist: rst2ansi
Requires-Dist: pygments
Requires-Dist: sphinx-rtd-theme
Requires-Dist: versioneer
